[
    {
        "Date": "2025-09-29",
        "LSTM_Predicted_Price": 244.0500030517578,
        "Transformer_Predicted_Price": 244.0500030517578,
        "TCN_GRU_Predicted_Price": 244.0500030517578
    },
    {
        "Date": "2025-09-30",
        "LSTM_Predicted_Price": 244.8501194934761,
        "Transformer_Predicted_Price": 239.5432603510926,
        "TCN_GRU_Predicted_Price": 244.0107565576891
    },
    {
        "Date": "2025-10-01",
        "LSTM_Predicted_Price": 240.77498640197064,
        "Transformer_Predicted_Price": 243.46638237402203,
        "TCN_GRU_Predicted_Price": 244.48607844063554
    },
    {
        "Date": "2025-10-02",
        "LSTM_Predicted_Price": 244.6188008319932,
        "Transformer_Predicted_Price": 247.34737769316234,
        "TCN_GRU_Predicted_Price": 244.11365859588113
    },
    {
        "Date": "2025-10-03",
        "LSTM_Predicted_Price": 243.66427314693192,
        "Transformer_Predicted_Price": 245.8117895167834,
        "TCN_GRU_Predicted_Price": 246.56378609105195
    },
    {
        "Date": "2025-10-04",
        "LSTM_Predicted_Price": 244.4557344129753,
        "Transformer_Predicted_Price": 250.26485558175045,
        "TCN_GRU_Predicted_Price": 246.82259766350217
    },
    {
        "Date": "2025-10-05",
        "LSTM_Predicted_Price": 244.28330003910924,
        "Transformer_Predicted_Price": 241.16027991138435,
        "TCN_GRU_Predicted_Price": 248.67477616490396
    },
    {
        "Date": "2025-10-06",
        "LSTM_Predicted_Price": 242.13252525018015,
        "Transformer_Predicted_Price": 243.91154933398684,
        "TCN_GRU_Predicted_Price": 252.06789595974078
    },
    {
        "Date": "2025-10-07",
        "LSTM_Predicted_Price": 246.1066182572522,
        "Transformer_Predicted_Price": 240.0967842919017,
        "TCN_GRU_Predicted_Price": 252.13256975982586
    },
    {
        "Date": "2025-10-08",
        "LSTM_Predicted_Price": 247.91361528697962,
        "Transformer_Predicted_Price": 239.8177821583813,
        "TCN_GRU_Predicted_Price": 253.9850973775574
    },
    {
        "Date": "2025-10-09",
        "LSTM_Predicted_Price": 242.4505556800632,
        "Transformer_Predicted_Price": 240.24080932443485,
        "TCN_GRU_Predicted_Price": 254.59258888433942
    },
    {
        "Date": "2025-10-10",
        "LSTM_Predicted_Price": 245.57564141273906,
        "Transformer_Predicted_Price": 237.17975734523952,
        "TCN_GRU_Predicted_Price": 254.19226882623298
    },
    {
        "Date": "2025-10-11",
        "LSTM_Predicted_Price": 245.77283395298946,
        "Transformer_Predicted_Price": 250.16311726465756,
        "TCN_GRU_Predicted_Price": 255.1109684479543
    },
    {
        "Date": "2025-10-12",
        "LSTM_Predicted_Price": 243.4842745859214,
        "Transformer_Predicted_Price": 247.72785630652834,
        "TCN_GRU_Predicted_Price": 254.5788569753695
    },
    {
        "Date": "2025-10-13",
        "LSTM_Predicted_Price": 247.0890316091518,
        "Transformer_Predicted_Price": 248.57437612707508,
        "TCN_GRU_Predicted_Price": 256.1044080572683
    },
    {
        "Date": "2025-10-14",
        "LSTM_Predicted_Price": 244.0909369414203,
        "Transformer_Predicted_Price": 237.90245724083707,
        "TCN_GRU_Predicted_Price": 256.82166755672733
    },
    {
        "Date": "2025-10-15",
        "LSTM_Predicted_Price": 243.21029099964107,
        "Transformer_Predicted_Price": 240.24307858057819,
        "TCN_GRU_Predicted_Price": 259.21672195088104
    },
    {
        "Date": "2025-10-16",
        "LSTM_Predicted_Price": 245.13848958184462,
        "Transformer_Predicted_Price": 242.2603163733802,
        "TCN_GRU_Predicted_Price": 259.3930838834567
    },
    {
        "Date": "2025-10-17",
        "LSTM_Predicted_Price": 245.41365143573785,
        "Transformer_Predicted_Price": 246.92110665454493,
        "TCN_GRU_Predicted_Price": 261.9085834113721
    },
    {
        "Date": "2025-10-18",
        "LSTM_Predicted_Price": 244.61260401714026,
        "Transformer_Predicted_Price": 246.9118841648342,
        "TCN_GRU_Predicted_Price": 264.69316435043766
    },
    {
        "Date": "2025-10-19",
        "LSTM_Predicted_Price": 247.3755397437617,
        "Transformer_Predicted_Price": 239.06328358374958,
        "TCN_GRU_Predicted_Price": 263.34109499139413
    },
    {
        "Date": "2025-10-20",
        "LSTM_Predicted_Price": 246.477117962193,
        "Transformer_Predicted_Price": 241.98175063527196,
        "TCN_GRU_Predicted_Price": 264.30590706166913
    },
    {
        "Date": "2025-10-21",
        "LSTM_Predicted_Price": 244.44755927225378,
        "Transformer_Predicted_Price": 245.59859581141973,
        "TCN_GRU_Predicted_Price": 266.1821454967958
    },
    {
        "Date": "2025-10-22",
        "LSTM_Predicted_Price": 244.57251382527465,
        "Transformer_Predicted_Price": 249.5144882170207,
        "TCN_GRU_Predicted_Price": 265.4851638374894
    },
    {
        "Date": "2025-10-23",
        "LSTM_Predicted_Price": 243.48239808564904,
        "Transformer_Predicted_Price": 246.0580619943903,
        "TCN_GRU_Predicted_Price": 267.5246723428263
    },
    {
        "Date": "2025-10-24",
        "LSTM_Predicted_Price": 245.55190150231647,
        "Transformer_Predicted_Price": 236.9481622999956,
        "TCN_GRU_Predicted_Price": 265.67831244692024
    },
    {
        "Date": "2025-10-25",
        "LSTM_Predicted_Price": 244.41762254697824,
        "Transformer_Predicted_Price": 250.7996145198358,
        "TCN_GRU_Predicted_Price": 267.0881605585364
    },
    {
        "Date": "2025-10-26",
        "LSTM_Predicted_Price": 243.59919204446214,
        "Transformer_Predicted_Price": 251.51995788020758,
        "TCN_GRU_Predicted_Price": 269.0480414476642
    },
    {
        "Date": "2025-10-27",
        "LSTM_Predicted_Price": 243.85960373342368,
        "Transformer_Predicted_Price": 244.20047218987747,
        "TCN_GRU_Predicted_Price": 268.5109259743531
    },
    {
        "Date": "2025-10-28",
        "LSTM_Predicted_Price": 244.57402666270355,
        "Transformer_Predicted_Price": 246.541238994756,
        "TCN_GRU_Predicted_Price": 267.7079875089694
    },
    {
        "Date": "2025-10-29",
        "LSTM_Predicted_Price": 247.36218604414898,
        "Transformer_Predicted_Price": 248.5788564533068,
        "TCN_GRU_Predicted_Price": 268.6167082222655
    }
]